sftpConfigReader/__init__.py
sftpConfigReader/reader.py
tests/__init__.py
tests/test_sftp_config.py
sftpConfigReader-1.0.0.dist-info/LICENSE
sftpConfigReader-1.0.0.dist-info/METADATA
sftpConfigReader-1.0.0.dist-info/WHEEL
sftpConfigReader-1.0.0.dist-info/top_level.txt
sftpConfigReader-1.0.0.dist-info/RECORD
