Metadata-Version: 2.1
Name: sftpConfigReader
Version: 1.0.0
Summary: SFTP configuration reader
Home-page: https://github.com/alv2017/sftp_config_reader.git
Author: Vitalija Alisauskaite (alv2017)
Author-email: alv2017@protonmail.com
License: UNKNOWN
Keywords: sftp,network
Platform: UNKNOWN
Classifier: Programming Language :: Python :: 3
Classifier: License :: OSI Approved :: MIT License
Classifier: Operating System :: OS Independent
Requires-Python: >=3.6
